syntaxlight/__init__.py
syntaxlight/asts/ast.py
syntaxlight/asts/c_ast.py
syntaxlight/asts/dot_ast.py
syntaxlight/asts/lua_ast.py
syntaxlight/asts/python_ast.py
syntaxlight/asts/rust_ast.py
syntaxlight/asts/verilog_ast.py
syntaxlight/asts/xml_ast.py
syntaxlight/css/_base.css
syntaxlight/css/all.css
syntaxlight/css/bnf.css
syntaxlight/css/c.css
syntaxlight/css/css.css
syntaxlight/css/diff.css
syntaxlight/css/dot.css
syntaxlight/css/index.css
syntaxlight/css/json.css
syntaxlight/css/lua.css
syntaxlight/css/makefile.css
syntaxlight/css/python.css
syntaxlight/css/riscvasm.css
syntaxlight/css/rust.css
syntaxlight/css/shell.css
syntaxlight/css/themes.json
syntaxlight/css/toml.css
syntaxlight/css/tree.css
syntaxlight/css/txt.css
syntaxlight/css/verilog.css
syntaxlight/css/x86asm.css
syntaxlight/css/xml.css
syntaxlight/css/yaml.css
syntaxlight/error.py
syntaxlight/example.py
syntaxlight/export.py
syntaxlight/gdt.py
syntaxlight/language.py
syntaxlight/lexers/__init__.py
syntaxlight/lexers/asm_lexer.py
syntaxlight/lexers/bnf_lexer.py
syntaxlight/lexers/c_lexer.py
syntaxlight/lexers/css_lexer.py
syntaxlight/lexers/diff_lexer.py
syntaxlight/lexers/dot_lexer.py
syntaxlight/lexers/json_lexer.py
syntaxlight/lexers/lexer.py
syntaxlight/lexers/lua_lexer.py
syntaxlight/lexers/makefile_lexer.py
syntaxlight/lexers/python_lexer.py
syntaxlight/lexers/rust_lexer.py
syntaxlight/lexers/shell_lexer.py
syntaxlight/lexers/toml_lexer.py
syntaxlight/lexers/tree_lexer.py
syntaxlight/lexers/txt_lexer.py
syntaxlight/lexers/verilog_lexer.py
syntaxlight/lexers/xml_lexer.py
syntaxlight/lexers/yaml_lexer.py
syntaxlight/parsers/__init__.py
syntaxlight/parsers/asm_parser.py
syntaxlight/parsers/bnf_parser.py
syntaxlight/parsers/c_parser.py
syntaxlight/parsers/css_parser.py
syntaxlight/parsers/diff_parser.py
syntaxlight/parsers/dot_parser.py
syntaxlight/parsers/json_parser.py
syntaxlight/parsers/lua_parser.py
syntaxlight/parsers/makefile_parser.py
syntaxlight/parsers/parser.py
syntaxlight-0.1.59.dist-info/LICENSE
syntaxlight-0.1.59.dist-info/METADATA
syntaxlight-0.1.59.dist-info/WHEEL
syntaxlight-0.1.59.dist-info/RECORD
